edlstrip/__init__.py
edlstrip/__main__.py
tests/__init__.py
tests/test_edlstrip.py
edlstrip-1.0.5.dist-info/LICENSE
edlstrip-1.0.5.dist-info/METADATA
edlstrip-1.0.5.dist-info/WHEEL
edlstrip-1.0.5.dist-info/entry_points.txt
edlstrip-1.0.5.dist-info/top_level.txt
edlstrip-1.0.5.dist-info/RECORD
