Metadata-Version: 2.1
Name: edlstrip
Version: 1.0.5
Summary: Strips commercials off Channels DVR recordings using outputted EDL files
Home-page: https://github.com/shuaiscott/edlstrip
Author: Scott C.
Author-email: shuaiscott@gmail.com
License: UNKNOWN
Platform: UNKNOWN
Classifier: Programming Language :: Python :: 3
Classifier: License :: OSI Approved :: MIT License
Classifier: Operating System :: OS Independent
Requires-Python: >=3
